{"site":{"title":"Shuhei Kagawa","author":"Shuhei Kagawa","perPage":3,"newPageExtension":"markdown","blogDir":"blog","sourceDir":"source","layoutDir":"_layouts","postDir":"_posts","cssFiles":["node_modules/highlight.js/styles/monokai-sublime.css","source/_css/style.css"]},"post":{"layout":"post","title":"ソフトウェア開発技術者","published":true,"date":"2008-12-16 00:36","comments":true,"tags":null,"categories":[],"url":"/blog/2008/12/16/software-develope/","content":"<p>ソフ開受かってました。</p>\n<blockquote><p>受験番号 SWxxx &#8211; xxxx の方は，合格です。<br />\n午前試験のスコアは，735 点です。<br />\n午後I試験のスコアは，740 点です。<br />\n午後II試験のスコアは，615 点です。</p></blockquote>\n<p>それぞれ 400-800 点で採点され、それぞれ 600 点以上で合格だとか。<br />\n午後 II がかなり危なかったです。<br />\nちょっと間違えたなとは思ったけど、まさかこんなにだとは。</p>\n<p>午前や午後 I については、試験直前に過去問だけで勉強したのでコンピュータの基礎が身についたかは疑問です。<br />\nやや過去問にオーバーフィットのきらいがあるかも。<br />\nどこかで紙面ではなく触って覚える必要がありますね。</p>\n<p>まあ、何はともあれ良かったです。</p>"}}